.editorconfig
.gitignore
CHANGELOG.md
LICENSE
Makefile
README.md
setup.cfg
setup.py
.github/ISSUE_TEMPLATE/bug_report.md
.github/ISSUE_TEMPLATE/feature_request.md
.github/workflows/automerge.yml
.github/workflows/conventional-prs.yml
.github/workflows/main.yml
.github/workflows/release-please.yml
docker/cada/Dockerfile
docker/cada/build.sh
gene_ranking_shootout/__init__.py
gene_ranking_shootout/models.py
gene_ranking_shootout/runner.py
gene_ranking_shootout.egg-info/PKG-INFO
gene_ranking_shootout.egg-info/SOURCES.txt
gene_ranking_shootout.egg-info/dependency_links.txt
gene_ranking_shootout.egg-info/entry_points.txt
gene_ranking_shootout.egg-info/not-zip-safe
gene_ranking_shootout.egg-info/requires.txt
gene_ranking_shootout.egg-info/top_level.txt
gene_ranking_shootout/cli/__init__.py
gene_ranking_shootout/data/cada_all_cases.json
gene_ranking_shootout/data/cada_cases_test.json
gene_ranking_shootout/data/cada_cases_train.json
gene_ranking_shootout/data/cada_cases_validate.json
gene_ranking_shootout/data/cada_clinvar_cases.json
gene_ranking_shootout/data/cada_collaborator_cases.json
gene_ranking_shootout/data/gnomad_counts.tsv
tests/test_example.py
tests/data/amelie/query.json
tests/data/amelie/response.json
tests/data/cada/query.txt
tests/data/cada/result.txt
tests/data/phen2gene/genes.txt
tests/data/phen2gene/output_file.associated_gene_list
tests/data/phen2gene/terms.txt